django_url_simplify-0.0.2.dist-info/DESCRIPTION.rst
django_url_simplify-0.0.2.dist-info/METADATA
django_url_simplify-0.0.2.dist-info/RECORD
django_url_simplify-0.0.2.dist-info/WHEEL
django_url_simplify-0.0.2.dist-info/metadata.json
django_url_simplify-0.0.2.dist-info/top_level.txt
url_simplify/__init__.py
url_simplify/admin.py
url_simplify/apps.py
url_simplify/models.py
url_simplify/tests.py
url_simplify/urls.py
url_simplify/views.py
url_simplify/templates/url_simplify/detail.html
url_simplify/templates/url_simplify/index.html
url_simplify/templates/url_simplify/urls_list.html
